oead.cpython-37m-darwin.so
oead-1.2.7.dist-info/LICENSE.md
oead-1.2.7.dist-info/RECORD
oead-1.2.7.dist-info/WHEEL
oead-1.2.7.dist-info/top_level.txt
oead-1.2.7.dist-info/METADATA
oead-1.2.7.data/data/data/botw_numbered_names.txt
oead-1.2.7.data/data/data/botw_resource_factory_info.tsv
oead-1.2.7.data/data/data/botw_hashed_names.txt
oead-1.2.7.data/data/data/aglenv_file_info.json
