Metadata-Version: 2.1
Name: oead
Version: 1.2.7
Summary: Library for recent Nintendo EAD formats in first-party games
Home-page: https://github.com/zeldamods/oead
Author: leoetlino
Author-email: leo@leolam.fr
Classifier: License :: OSI Approved :: GNU General Public License v2 or later (GPLv2+)
Classifier: Topic :: Software Development :: Libraries
Classifier: Operating System :: OS Independent
Classifier: Programming Language :: C++
Classifier: Programming Language :: Python :: 3 :: Only
Requires-Python: >=3.6
License-File: LICENSE.md
